{
  "version": "2.0.0",
  "scrollSpeed": {
    "easy": 1.4,
    "hard": 2,
    "normal": 1.7
  },
  "events": [
    {
      "t": 0,
      "e": "FocusCamera",
      "v": {
        "char": 1
      }
    },
    {
      "t": 3000,
      "e": "FocusCamera",
      "v": {
        "char": 0
      }
    },
    {
      "t": 6000,
      "e": "FocusCamera",
      "v": {
        "char": 1
      }
    },
    {
      "t": 9000,
      "e": "FocusCamera",
      "v": {
        "char": 0
      }
    },
    {
      "t": 12000,
      "e": "FocusCamera",
      "v": {
        "char": 1
      }
    },
    {
      "t": 12750,
      "e": "FocusCamera",
      "v": {
        "char": 0
      }
    },
    {
      "t": 13500,
      "e": "FocusCamera",
      "v": {
        "char": 1
      }
    },
    {
      "t": 14250,
      "e": "FocusCamera",
      "v": {
        "char": 0
      }
    },
    {
      "t": 15000,
      "e": "FocusCamera",
      "v": {
        "x": 0,
        "duration": 4,
        "y": 0,
        "ease": "linear",
        "char": 2
      }
    },
    {
      "t": 15000,
      "e": "ZoomCamera",
      "v": {
        "duration": 4,
        "ease": "linear",
        "zoom": 0.7,
        "mode": "stage"
      }
    },
    {
      "t": 16500,
      "e": "ZoomCamera",
      "v": {
        "duration": 4,
        "ease": "linear",
        "zoom": 1,
        "mode": "stage"
      }
    },
    {
      "t": 16500,
      "e": "FocusCamera",
      "v": {
        "x": 0,
        "duration": 4,
        "y": 0,
        "char": 1,
        "ease": "linear"
      }
    },
    {
      "t": 18000,
      "e": "FocusCamera",
      "v": {
        "char": 0
      }
    },
    {
      "t": 24000,
      "e": "FocusCamera",
      "v": {
        "char": 1
      }
    },
    {
      "t": 28500,
      "e": "FocusCamera",
      "v": {
        "char": 0
      }
    },
    {
      "t": 31500,
      "e": "ZoomCamera",
      "v": {
        "ease": "linear",
        "duration": 4,
        "mode": "stage",
        "zoom": 0.7
      }
    },
    {
      "t": 31500,
      "e": "FocusCamera",
      "v": {
        "duration": 4,
        "x": 0,
        "y": 0,
        "char": 2,
        "ease": "linear"
      }
    },
    {
      "t": 38625,
      "e": "ZoomCamera",
      "v": {
        "ease": "linear",
        "duration": 4,
        "mode": "stage",
        "zoom": 1
      }
    },
    {
      "t": 38625,
      "e": "FocusCamera",
      "v": {
        "duration": 4,
        "x": 0,
        "y": 0,
        "ease": "linear",
        "char": 1
      }
    }
  ],
  "notes": {
    "easy": [
      {
        "t": 0,
        "d": 4,
        "l": 0,
        "p": []
      },
      {
        "t": 187.5,
        "d": 7,
        "l": 0,
        "p": []
      },
      {
        "t": 375,
        "d": 5,
        "l": 0,
        "p": []
      },
      {
        "t": 562.5,
        "d": 6,
        "l": 0,
        "p": []
      },
      {
        "t": 750,
        "d": 4,
        "l": 0,
        "p": []
      },
      {
        "t": 937.5,
        "d": 5,
        "l": 0,
        "p": []
      },
      {
        "t": 1125,
        "d": 6,
        "l": 0,
        "p": []
      },
      {
        "t": 1218.75,
        "d": 4,
        "l": 0,
        "p": []
      },
      {
        "t": 1312.5,
        "d": 6,
        "l": 0,
        "p": []
      },
      {
        "t": 1500,
        "d": 5,
        "l": 0,
        "p": []
      },
      {
        "t": 1593.75,
        "d": 7,
        "l": 0,
        "p": []
      },
      {
        "t": 1687.5,
        "d": 6,
        "l": 0,
        "p": []
      },
      {
        "t": 1781.25,
        "d": 4,
        "l": 0,
        "p": []
      },
      {
        "t": 2062.5,
        "d": 7,
        "l": 0,
        "p": []
      },
      {
        "t": 2250,
        "d": 5,
        "l": 0,
        "p": []
      },
      {
        "t": 2437.5,
        "d": 4,
        "l": 0,
        "p": []
      },
      {
        "t": 3000,
        "d": 3,
        "l": 0,
        "p": []
      },
      {
        "t": 3187.5,
        "d": 2,
        "l": 0,
        "p": []
      },
      {
        "t": 3375,
        "d": 0,
        "l": 0,
        "p": []
      },
      {
        "t": 3562.5,
        "d": 2,
        "l": 0,
        "p": []
      },
      {
        "t": 3750,
        "d": 3,
        "l": 0,
        "p": []
      },
      {
        "t": 3937.5,
        "d": 2,
        "l": 0,
        "p": []
      },
      {
        "t": 4125,
        "d": 0,
        "l": 0,
        "p": []
      },
      {
        "t": 4312.5,
        "d": 1,
        "l": 0,
        "p": []
      },
      {
        "t": 4500,
        "d": 3,
        "l": 0,
        "p": []
      },
      {
        "t": 4687.5,
        "d": 0,
        "l": 0,
        "p": []
      },
      {
        "t": 4875,
        "d": 3,
        "l": 0,
        "p": []
      },
      {
        "t": 5156.25,
        "d": 2,
        "l": 0,
        "p": []
      },
      {
        "t": 5437.5,
        "d": 0,
        "l": 0,
        "p": []
      },
      {
        "t": 5625,
        "d": 2,
        "l": 0,
        "p": []
      },
      {
        "t": 6000,
        "d": 6,
        "l": 0,
        "p": []
      },
      {
        "t": 6187.5,
        "d": 4,
        "l": 0,
        "p": []
      },
      {
        "t": 6375,
        "d": 6,
        "l": 0,
        "p": []
      },
      {
        "t": 6562.5,
        "d": 4,
        "l": 0,
        "p": []
      },
      {
        "t": 6656.25,
        "d": 7,
        "l": 0,
        "p": []
      },
      {
        "t": 6750,
        "d": 4,
        "l": 0,
        "p": []
      },
      {
        "t": 6843.75,
        "d": 7,
        "l": 0,
        "p": []
      },
      {
        "t": 6937.5,
        "d": 6,
        "l": 0,
        "p": []
      },
      {
        "t": 7125,
        "d": 4,
        "l": 0,
        "p": []
      },
      {
        "t": 7500,
        "d": 4,
        "l": 0,
        "p": []
      },
      {
        "t": 7593.75,
        "d": 5,
        "l": 0,
        "p": []
      },
      {
        "t": 7687.5,
        "d": 7,
        "l": 0,
        "p": []
      },
      {
        "t": 7875,
        "d": 6,
        "l": 0,
        "p": []
      },
      {
        "t": 8062.5,
        "d": 6,
        "l": 0,
        "p": []
      },
      {
        "t": 8156.25,
        "d": 5,
        "l": 0,
        "p": []
      },
      {
        "t": 8250,
        "d": 6,
        "l": 0,
        "p": []
      },
      {
        "t": 8437.5,
        "d": 4,
        "l": 0,
        "p": []
      },
      {
        "t": 8625,
        "d": 7,
        "l": 0,
        "p": []
      },
      {
        "t": 9000,
        "d": 1,
        "l": 0,
        "p": []
      },
      {
        "t": 9187.5,
        "d": 2,
        "l": 0,
        "p": []
      },
      {
        "t": 9375,
        "d": 1,
        "l": 0,
        "p": []
      },
      {
        "t": 9562.5,
        "d": 2,
        "l": 0,
        "p": []
      },
      {
        "t": 9656.25,
        "d": 1,
        "l": 0,
        "p": []
      },
      {
        "t": 9843.75,
        "d": 1,
        "l": 0,
        "p": []
      },
      {
        "t": 9937.5,
        "d": 3,
        "l": 0,
        "p": []
      },
      {
        "t": 10125,
        "d": 2,
        "l": 0,
        "p": []
      },
      {
        "t": 10500,
        "d": 2,
        "l": 0,
        "p": []
      },
      {
        "t": 10593.75,
        "d": 1,
        "l": 0,
        "p": []
      },
      {
        "t": 10687.5,
        "d": 3,
        "l": 0,
        "p": []
      },
      {
        "t": 10875,
        "d": 2,
        "l": 0,
        "p": []
      },
      {
        "t": 11062.5,
        "d": 0,
        "l": 0,
        "p": []
      },
      {
        "t": 11156.25,
        "d": 1,
        "l": 0,
        "p": []
      },
      {
        "t": 11250,
        "d": 2,
        "l": 0,
        "p": []
      },
      {
        "t": 11437.5,
        "d": 3,
        "l": 0,
        "p": []
      },
      {
        "t": 11625,
        "d": 2,
        "l": 0,
        "p": []
      },
      {
        "t": 12000,
        "d": 4,
        "l": 0,
        "p": []
      },
      {
        "t": 12187.5,
        "d": 7,
        "l": 0,
        "p": []
      },
      {
        "t": 12375,
        "d": 6,
        "l": 0,
        "p": []
      },
      {
        "t": 12562.5,
        "d": 5,
        "l": 0,
        "p": []
      },
      {
        "t": 12750,
        "d": 3,
        "l": 0,
        "p": []
      },
      {
        "t": 12937.5,
        "d": 0,
        "l": 0,
        "p": []
      },
      {
        "t": 13125,
        "d": 2,
        "l": 0,
        "p": []
      },
      {
        "t": 13312.5,
        "d": 1,
        "l": 0,
        "p": []
      },
      {
        "t": 13500,
        "d": 4,
        "l": 0,
        "p": []
      },
      {
        "t": 13687.5,
        "d": 5,
        "l": 0,
        "p": []
      },
      {
        "t": 13875,
        "d": 4,
        "l": 0,
        "p": []
      },
      {
        "t": 14062.5,
        "d": 5,
        "l": 0,
        "p": []
      },
      {
        "t": 14250,
        "d": 3,
        "l": 0,
        "p": []
      },
      {
        "t": 14437.5,
        "d": 1,
        "l": 0,
        "p": []
      },
      {
        "t": 14625,
        "d": 3,
        "l": 0,
        "p": []
      },
      {
        "t": 14812.5,
        "d": 1,
        "l": 0,
        "p": []
      },
      {
        "t": 15000,
        "d": 6,
        "l": 0,
        "p": []
      },
      {
        "t": 15000,
        "d": 2,
        "l": 0,
        "p": []
      },
      {
        "t": 15187.5,
        "d": 5,
        "l": 0,
        "p": []
      },
      {
        "t": 15187.5,
        "d": 1,
        "l": 0,
        "p": []
      },
      {
        "t": 15375,
        "d": 6,
        "l": 0,
        "p": []
      },
      {
        "t": 15375,
        "d": 2,
        "l": 0,
        "p": []
      },
      {
        "t": 15562.5,
        "d": 5,
        "l": 0,
        "p": []
      },
      {
        "t": 15562.5,
        "d": 1,
        "l": 0,
        "p": []
      },
      {
        "t": 15750,
        "d": 4,
        "l": 0,
        "p": []
      },
      {
        "t": 15750,
        "d": 3,
        "l": 0,
        "p": []
      },
      {
        "t": 15843.75,
        "d": 7,
        "l": 0,
        "p": []
      },
      {
        "t": 15843.75,
        "d": 0,
        "l": 0,
        "p": []
      },
      {
        "t": 15937.5,
        "d": 6,
        "l": 0,
        "p": []
      },
      {
        "t": 15937.5,
        "d": 2,
        "l": 0,
        "p": []
      },
      {
        "t": 16125,
        "d": 5,
        "l": 0,
        "p": []
      },
      {
        "t": 16125,
        "d": 1,
        "l": 0,
        "p": []
      },
      {
        "t": 16218.75,
        "d": 6,
        "l": 0,
        "p": []
      },
      {
        "t": 16218.75,
        "d": 2,
        "l": 0,
        "p": []
      },
      {
        "t": 16312.5,
        "d": 1,
        "l": 0,
        "p": []
      },
      {
        "t": 16500,
        "d": 4,
        "l": 0,
        "p": []
      },
      {
        "t": 16593.75,
        "d": 5,
        "l": 0,
        "p": []
      },
      {
        "t": 16687.5,
        "d": 5,
        "l": 281.25,
        "p": []
      },
      {
        "t": 17062.5,
        "d": 7,
        "l": 0,
        "p": []
      },
      {
        "t": 17250,
        "d": 6,
        "l": 0,
        "p": []
      },
      {
        "t": 17343.75,
        "d": 4,
        "l": 0,
        "p": []
      },
      {
        "t": 17437.5,
        "d": 7,
        "l": 0,
        "p": []
      },
      {
        "t": 17531.25,
        "d": 6,
        "l": 0,
        "p": []
      },
      {
        "t": 17625,
        "d": 5,
        "l": 0,
        "p": []
      },
      {
        "t": 17718.75,
        "d": 5,
        "l": 187.5,
        "p": []
      },
      {
        "t": 18000,
        "d": 3,
        "l": 0,
        "p": []
      },
      {
        "t": 18093.75,
        "d": 0,
        "l": 0,
        "p": []
      },
      {
        "t": 18187.5,
        "d": 3,
        "l": 0,
        "p": []
      },
      {
        "t": 18562.5,
        "d": 1,
        "l": 0,
        "p": []
      },
      {
        "t": 18750,
        "d": 1,
        "l": 0,
        "p": []
      },
      {
        "t": 18843.75,
        "d": 0,
        "l": 0,
        "p": []
      },
      {
        "t": 18937.5,
        "d": 2,
        "l": 0,
        "p": []
      },
      {
        "t": 19031.25,
        "d": 1,
        "l": 0,
        "p": []
      },
      {
        "t": 19218.75,
        "d": 3,
        "l": 0,
        "p": []
      },
      {
        "t": 19312.5,
        "d": 1,
        "l": 0,
        "p": []
      },
      {
        "t": 19500,
        "d": 2,
        "l": 0,
        "p": []
      },
      {
        "t": 19687.5,
        "d": 0,
        "l": 0,
        "p": []
      },
      {
        "t": 19875,
        "d": 2,
        "l": 0,
        "p": []
      },
      {
        "t": 20062.5,
        "d": 3,
        "l": 0,
        "p": []
      },
      {
        "t": 20250,
        "d": 1,
        "l": 0,
        "p": []
      },
      {
        "t": 20437.5,
        "d": 2,
        "l": 0,
        "p": []
      },
      {
        "t": 20625,
        "d": 3,
        "l": 0,
        "p": []
      },
      {
        "t": 20812.5,
        "d": 1,
        "l": 0,
        "p": []
      },
      {
        "t": 21000,
        "d": 0,
        "l": 0,
        "p": []
      },
      {
        "t": 21187.5,
        "d": 3,
        "l": 0,
        "p": []
      },
      {
        "t": 21375,
        "d": 2,
        "l": 0,
        "p": []
      },
      {
        "t": 21562.5,
        "d": 1,
        "l": 0,
        "p": []
      },
      {
        "t": 21750,
        "d": 0,
        "l": 281.25,
        "p": []
      },
      {
        "t": 22125,
        "d": 2,
        "l": 281.25,
        "p": []
      },
      {
        "t": 22500,
        "d": 1,
        "l": 281.25,
        "p": []
      },
      {
        "t": 22875,
        "d": 2,
        "l": 281.25,
        "p": []
      },
      {
        "t": 23250,
        "d": 3,
        "l": 281.25,
        "p": []
      },
      {
        "t": 23625,
        "d": 0,
        "l": 281.25,
        "p": []
      },
      {
        "t": 24000,
        "d": 6,
        "l": 0,
        "p": []
      },
      {
        "t": 24375,
        "d": 7,
        "l": 0,
        "p": []
      },
      {
        "t": 24750,
        "d": 4,
        "l": 0,
        "p": []
      },
      {
        "t": 25125,
        "d": 5,
        "l": 0,
        "p": []
      },
      {
        "t": 25500,
        "d": 4,
        "l": 0,
        "p": []
      },
      {
        "t": 25500,
        "d": 6,
        "l": 0,
        "p": []
      },
      {
        "t": 26250,
        "d": 6,
        "l": 0,
        "p": []
      },
      {
        "t": 26437.5,
        "d": 7,
        "l": 0,
        "p": []
      },
      {
        "t": 26625,
        "d": 5,
        "l": 0,
        "p": []
      },
      {
        "t": 26812.5,
        "d": 4,
        "l": 0,
        "p": []
      },
      {
        "t": 27000,
        "d": 5,
        "l": 0,
        "p": []
      },
      {
        "t": 27187.5,
        "d": 6,
        "l": 0,
        "p": []
      },
      {
        "t": 27375,
        "d": 5,
        "l": 0,
        "p": []
      },
      {
        "t": 27562.5,
        "d": 4,
        "l": 0,
        "p": []
      },
      {
        "t": 27750,
        "d": 6,
        "l": 0,
        "p": []
      },
      {
        "t": 27937.5,
        "d": 5,
        "l": 0,
        "p": []
      },
      {
        "t": 28125,
        "d": 4,
        "l": 0,
        "p": []
      },
      {
        "t": 28500,
        "d": 2,
        "l": 0,
        "p": []
      },
      {
        "t": 28875,
        "d": 3,
        "l": 0,
        "p": []
      },
      {
        "t": 29062.5,
        "d": 1,
        "l": 0,
        "p": []
      },
      {
        "t": 29250,
        "d": 0,
        "l": 0,
        "p": []
      },
      {
        "t": 29437.5,
        "d": 2,
        "l": 0,
        "p": []
      },
      {
        "t": 29625,
        "d": 1,
        "l": 0,
        "p": []
      },
      {
        "t": 29812.5,
        "d": 3,
        "l": 0,
        "p": []
      },
      {
        "t": 30000,
        "d": 0,
        "l": 0,
        "p": []
      },
      {
        "t": 30375,
        "d": 2,
        "l": 0,
        "p": []
      },
      {
        "t": 30562.5,
        "d": 1,
        "l": 0,
        "p": []
      },
      {
        "t": 30750,
        "d": 2,
        "l": 0,
        "p": []
      },
      {
        "t": 30937.5,
        "d": 3,
        "l": 0,
        "p": []
      },
      {
        "t": 38625,
        "d": 5,
        "l": 468.75,
        "p": []
      }
    ],
    "hard": [
      {
        "t": 0,
        "d": 4,
        "l": 0,
        "p": []
      },
      {
        "t": 187.5,
        "d": 7,
        "l": 0,
        "p": []
      },
      {
        "t": 375,
        "d": 5,
        "l": 0,
        "p": []
      },
      {
        "t": 562.5,
        "d": 6,
        "l": 0,
        "p": []
      },
      {
        "t": 750,
        "d": 4,
        "l": 0,
        "p": []
      },
      {
        "t": 937.5,
        "d": 5,
        "l": 0,
        "p": []
      },
      {
        "t": 1125,
        "d": 6,
        "l": 0,
        "p": []
      },
      {
        "t": 1218.75,
        "d": 7,
        "l": 0,
        "p": []
      },
      {
        "t": 1312.5,
        "d": 5,
        "l": 0,
        "p": []
      },
      {
        "t": 1500,
        "d": 5,
        "l": 0,
        "p": []
      },
      {
        "t": 1593.75,
        "d": 7,
        "l": 0,
        "p": []
      },
      {
        "t": 1687.5,
        "d": 6,
        "l": 0,
        "p": []
      },
      {
        "t": 1781.25,
        "d": 4,
        "l": 0,
        "p": []
      },
      {
        "t": 2062.5,
        "d": 7,
        "l": 0,
        "p": []
      },
      {
        "t": 2250,
        "d": 5,
        "l": 0,
        "p": []
      },
      {
        "t": 2437.5,
        "d": 4,
        "l": 0,
        "p": []
      },
      {
        "t": 3000,
        "d": 3,
        "l": 0,
        "p": []
      },
      {
        "t": 3187.5,
        "d": 2,
        "l": 0,
        "p": []
      },
      {
        "t": 3375,
        "d": 0,
        "l": 0,
        "p": []
      },
      {
        "t": 3562.5,
        "d": 2,
        "l": 0,
        "p": []
      },
      {
        "t": 3750,
        "d": 3,
        "l": 0,
        "p": []
      },
      {
        "t": 3937.5,
        "d": 2,
        "l": 0,
        "p": []
      },
      {
        "t": 4125,
        "d": 0,
        "l": 0,
        "p": []
      },
      {
        "t": 4312.5,
        "d": 1,
        "l": 0,
        "p": []
      },
      {
        "t": 4500,
        "d": 3,
        "l": 0,
        "p": []
      },
      {
        "t": 4687.5,
        "d": 0,
        "l": 0,
        "p": []
      },
      {
        "t": 4875,
        "d": 3,
        "l": 0,
        "p": []
      },
      {
        "t": 5156.25,
        "d": 2,
        "l": 0,
        "p": []
      },
      {
        "t": 5437.5,
        "d": 0,
        "l": 0,
        "p": []
      },
      {
        "t": 5625,
        "d": 2,
        "l": 0,
        "p": []
      },
      {
        "t": 6000,
        "d": 6,
        "l": 0,
        "p": []
      },
      {
        "t": 6187.5,
        "d": 4,
        "l": 0,
        "p": []
      },
      {
        "t": 6375,
        "d": 6,
        "l": 0,
        "p": []
      },
      {
        "t": 6562.5,
        "d": 4,
        "l": 0,
        "p": []
      },
      {
        "t": 6656.25,
        "d": 7,
        "l": 0,
        "p": []
      },
      {
        "t": 6750,
        "d": 6,
        "l": 0,
        "p": []
      },
      {
        "t": 6843.75,
        "d": 5,
        "l": 0,
        "p": []
      },
      {
        "t": 6937.5,
        "d": 6,
        "l": 0,
        "p": []
      },
      {
        "t": 7125,
        "d": 4,
        "l": 0,
        "p": []
      },
      {
        "t": 7500,
        "d": 4,
        "l": 0,
        "p": []
      },
      {
        "t": 7593.75,
        "d": 5,
        "l": 0,
        "p": []
      },
      {
        "t": 7687.5,
        "d": 7,
        "l": 0,
        "p": []
      },
      {
        "t": 7875,
        "d": 6,
        "l": 0,
        "p": []
      },
      {
        "t": 8062.5,
        "d": 6,
        "l": 0,
        "p": []
      },
      {
        "t": 8156.25,
        "d": 5,
        "l": 0,
        "p": []
      },
      {
        "t": 8250,
        "d": 6,
        "l": 0,
        "p": []
      },
      {
        "t": 8437.5,
        "d": 4,
        "l": 0,
        "p": []
      },
      {
        "t": 8625,
        "d": 7,
        "l": 0,
        "p": []
      },
      {
        "t": 9000,
        "d": 1,
        "l": 0,
        "p": []
      },
      {
        "t": 9187.5,
        "d": 2,
        "l": 0,
        "p": []
      },
      {
        "t": 9375,
        "d": 1,
        "l": 0,
        "p": []
      },
      {
        "t": 9562.5,
        "d": 2,
        "l": 0,
        "p": []
      },
      {
        "t": 9656.25,
        "d": 3,
        "l": 0,
        "p": []
      },
      {
        "t": 9750,
        "d": 0,
        "l": 0,
        "p": []
      },
      {
        "t": 9843.75,
        "d": 1,
        "l": 0,
        "p": []
      },
      {
        "t": 9937.5,
        "d": 2,
        "l": 0,
        "p": []
      },
      {
        "t": 10125,
        "d": 2,
        "l": 0,
        "p": []
      },
      {
        "t": 10500,
        "d": 2,
        "l": 0,
        "p": []
      },
      {
        "t": 10593.75,
        "d": 1,
        "l": 0,
        "p": []
      },
      {
        "t": 10687.5,
        "d": 3,
        "l": 0,
        "p": []
      },
      {
        "t": 10875,
        "d": 2,
        "l": 0,
        "p": []
      },
      {
        "t": 11062.5,
        "d": 0,
        "l": 0,
        "p": []
      },
      {
        "t": 11156.25,
        "d": 1,
        "l": 0,
        "p": []
      },
      {
        "t": 11250,
        "d": 2,
        "l": 0,
        "p": []
      },
      {
        "t": 11437.5,
        "d": 3,
        "l": 0,
        "p": []
      },
      {
        "t": 11625,
        "d": 2,
        "l": 0,
        "p": []
      },
      {
        "t": 12000,
        "d": 4,
        "l": 0,
        "p": []
      },
      {
        "t": 12187.5,
        "d": 7,
        "l": 0,
        "p": []
      },
      {
        "t": 12375,
        "d": 6,
        "l": 0,
        "p": []
      },
      {
        "t": 12562.5,
        "d": 5,
        "l": 0,
        "p": []
      },
      {
        "t": 12750,
        "d": 3,
        "l": 0,
        "p": []
      },
      {
        "t": 12937.5,
        "d": 0,
        "l": 0,
        "p": []
      },
      {
        "t": 13125,
        "d": 2,
        "l": 0,
        "p": []
      },
      {
        "t": 13312.5,
        "d": 1,
        "l": 0,
        "p": []
      },
      {
        "t": 13500,
        "d": 4,
        "l": 0,
        "p": []
      },
      {
        "t": 13687.5,
        "d": 5,
        "l": 0,
        "p": []
      },
      {
        "t": 13875,
        "d": 4,
        "l": 0,
        "p": []
      },
      {
        "t": 14062.5,
        "d": 5,
        "l": 0,
        "p": []
      },
      {
        "t": 14250,
        "d": 3,
        "l": 0,
        "p": []
      },
      {
        "t": 14437.5,
        "d": 1,
        "l": 0,
        "p": []
      },
      {
        "t": 14625,
        "d": 3,
        "l": 0,
        "p": []
      },
      {
        "t": 14812.5,
        "d": 1,
        "l": 0,
        "p": []
      },
      {
        "t": 15000,
        "d": 6,
        "l": 0,
        "p": []
      },
      {
        "t": 15000,
        "d": 2,
        "l": 0,
        "p": []
      },
      {
        "t": 15187.5,
        "d": 5,
        "l": 0,
        "p": []
      },
      {
        "t": 15187.5,
        "d": 1,
        "l": 0,
        "p": []
      },
      {
        "t": 15375,
        "d": 6,
        "l": 0,
        "p": []
      },
      {
        "t": 15375,
        "d": 2,
        "l": 0,
        "p": []
      },
      {
        "t": 15562.5,
        "d": 5,
        "l": 0,
        "p": []
      },
      {
        "t": 15562.5,
        "d": 1,
        "l": 0,
        "p": []
      },
      {
        "t": 15750,
        "d": 4,
        "l": 0,
        "p": []
      },
      {
        "t": 15750,
        "d": 3,
        "l": 0,
        "p": []
      },
      {
        "t": 15843.75,
        "d": 7,
        "l": 0,
        "p": []
      },
      {
        "t": 15843.75,
        "d": 0,
        "l": 0,
        "p": []
      },
      {
        "t": 15937.5,
        "d": 6,
        "l": 0,
        "p": []
      },
      {
        "t": 15937.5,
        "d": 2,
        "l": 0,
        "p": []
      },
      {
        "t": 16125,
        "d": 5,
        "l": 0,
        "p": []
      },
      {
        "t": 16125,
        "d": 1,
        "l": 0,
        "p": []
      },
      {
        "t": 16218.75,
        "d": 6,
        "l": 0,
        "p": []
      },
      {
        "t": 16218.75,
        "d": 2,
        "l": 0,
        "p": []
      },
      {
        "t": 16312.5,
        "d": 1,
        "l": 0,
        "p": []
      },
      {
        "t": 16500,
        "d": 4,
        "l": 0,
        "p": []
      },
      {
        "t": 16593.75,
        "d": 5,
        "l": 0,
        "p": []
      },
      {
        "t": 16687.5,
        "d": 5,
        "l": 281.25,
        "p": []
      },
      {
        "t": 17062.5,
        "d": 7,
        "l": 0,
        "p": []
      },
      {
        "t": 17250,
        "d": 6,
        "l": 0,
        "p": []
      },
      {
        "t": 17343.75,
        "d": 4,
        "l": 0,
        "p": []
      },
      {
        "t": 17437.5,
        "d": 7,
        "l": 0,
        "p": []
      },
      {
        "t": 17531.25,
        "d": 6,
        "l": 0,
        "p": []
      },
      {
        "t": 17625,
        "d": 5,
        "l": 0,
        "p": []
      },
      {
        "t": 17718.75,
        "d": 5,
        "l": 187.5,
        "p": []
      },
      {
        "t": 18000,
        "d": 3,
        "l": 0,
        "p": []
      },
      {
        "t": 18093.75,
        "d": 2,
        "l": 0,
        "p": []
      },
      {
        "t": 18187.5,
        "d": 3,
        "l": 0,
        "p": []
      },
      {
        "t": 18562.5,
        "d": 1,
        "l": 0,
        "p": []
      },
      {
        "t": 18750,
        "d": 1,
        "l": 0,
        "p": []
      },
      {
        "t": 18843.75,
        "d": 0,
        "l": 0,
        "p": []
      },
      {
        "t": 18937.5,
        "d": 2,
        "l": 0,
        "p": []
      },
      {
        "t": 19031.25,
        "d": 1,
        "l": 0,
        "p": []
      },
      {
        "t": 19218.75,
        "d": 3,
        "l": 0,
        "p": []
      },
      {
        "t": 19312.5,
        "d": 1,
        "l": 0,
        "p": []
      },
      {
        "t": 19500,
        "d": 2,
        "l": 0,
        "p": []
      },
      {
        "t": 19687.5,
        "d": 0,
        "l": 0,
        "p": []
      },
      {
        "t": 19875,
        "d": 2,
        "l": 0,
        "p": []
      },
      {
        "t": 20062.5,
        "d": 3,
        "l": 0,
        "p": []
      },
      {
        "t": 20250,
        "d": 1,
        "l": 0,
        "p": []
      },
      {
        "t": 20437.5,
        "d": 2,
        "l": 0,
        "p": []
      },
      {
        "t": 20625,
        "d": 3,
        "l": 0,
        "p": []
      },
      {
        "t": 20812.5,
        "d": 1,
        "l": 0,
        "p": []
      },
      {
        "t": 21000,
        "d": 0,
        "l": 0,
        "p": []
      },
      {
        "t": 21187.5,
        "d": 3,
        "l": 0,
        "p": []
      },
      {
        "t": 21375,
        "d": 2,
        "l": 0,
        "p": []
      },
      {
        "t": 21562.5,
        "d": 1,
        "l": 0,
        "p": []
      },
      {
        "t": 21750,
        "d": 0,
        "l": 281.25,
        "p": []
      },
      {
        "t": 22125,
        "d": 2,
        "l": 281.25,
        "p": []
      },
      {
        "t": 22500,
        "d": 1,
        "l": 281.25,
        "p": []
      },
      {
        "t": 22500,
        "d": 3,
        "l": 281.25,
        "p": []
      },
      {
        "t": 22875,
        "d": 2,
        "l": 281.25,
        "p": []
      },
      {
        "t": 22875,
        "d": 0,
        "l": 281.25,
        "p": []
      },
      {
        "t": 23250,
        "d": 1,
        "l": 281.25,
        "p": []
      },
      {
        "t": 23250,
        "d": 3,
        "l": 281.25,
        "p": []
      },
      {
        "t": 23625,
        "d": 2,
        "l": 281.25,
        "p": []
      },
      {
        "t": 23625,
        "d": 0,
        "l": 281.25,
        "p": []
      },
      {
        "t": 24000,
        "d": 4,
        "l": 0,
        "p": []
      },
      {
        "t": 24000,
        "d": 6,
        "l": 0,
        "p": []
      },
      {
        "t": 24375,
        "d": 5,
        "l": 0,
        "p": []
      },
      {
        "t": 24375,
        "d": 7,
        "l": 0,
        "p": []
      },
      {
        "t": 24750,
        "d": 7,
        "l": 0,
        "p": []
      },
      {
        "t": 24750,
        "d": 4,
        "l": 0,
        "p": []
      },
      {
        "t": 25125,
        "d": 5,
        "l": 0,
        "p": []
      },
      {
        "t": 25125,
        "d": 6,
        "l": 0,
        "p": []
      },
      {
        "t": 25500,
        "d": 4,
        "l": 0,
        "p": []
      },
      {
        "t": 25500,
        "d": 5,
        "l": 0,
        "p": []
      },
      {
        "t": 26250,
        "d": 6,
        "l": 0,
        "p": []
      },
      {
        "t": 26437.5,
        "d": 7,
        "l": 0,
        "p": []
      },
      {
        "t": 26625,
        "d": 5,
        "l": 0,
        "p": []
      },
      {
        "t": 26812.5,
        "d": 4,
        "l": 0,
        "p": []
      },
      {
        "t": 27000,
        "d": 5,
        "l": 0,
        "p": []
      },
      {
        "t": 27187.5,
        "d": 6,
        "l": 0,
        "p": []
      },
      {
        "t": 27375,
        "d": 5,
        "l": 0,
        "p": []
      },
      {
        "t": 27562.5,
        "d": 4,
        "l": 0,
        "p": []
      },
      {
        "t": 27750,
        "d": 6,
        "l": 0,
        "p": []
      },
      {
        "t": 27937.5,
        "d": 5,
        "l": 0,
        "p": []
      },
      {
        "t": 28125,
        "d": 4,
        "l": 0,
        "p": []
      },
      {
        "t": 28500,
        "d": 2,
        "l": 0,
        "p": []
      },
      {
        "t": 28875,
        "d": 3,
        "l": 0,
        "p": []
      },
      {
        "t": 29062.5,
        "d": 1,
        "l": 0,
        "p": []
      },
      {
        "t": 29250,
        "d": 0,
        "l": 0,
        "p": []
      },
      {
        "t": 29437.5,
        "d": 2,
        "l": 0,
        "p": []
      },
      {
        "t": 29625,
        "d": 1,
        "l": 0,
        "p": []
      },
      {
        "t": 29812.5,
        "d": 3,
        "l": 0,
        "p": []
      },
      {
        "t": 30000,
        "d": 0,
        "l": 0,
        "p": []
      },
      {
        "t": 30375,
        "d": 2,
        "l": 0,
        "p": []
      },
      {
        "t": 30562.5,
        "d": 1,
        "l": 0,
        "p": []
      },
      {
        "t": 30750,
        "d": 2,
        "l": 0,
        "p": []
      },
      {
        "t": 30937.5,
        "d": 3,
        "l": 0,
        "p": []
      },
      {
        "t": 38625,
        "d": 5,
        "l": 468.75,
        "p": []
      }
    ],
    "normal": [
      {
        "t": 0,
        "d": 4,
        "l": 0,
        "p": []
      },
      {
        "t": 187.5,
        "d": 7,
        "l": 0,
        "p": []
      },
      {
        "t": 375,
        "d": 5,
        "l": 0,
        "p": []
      },
      {
        "t": 562.5,
        "d": 6,
        "l": 0,
        "p": []
      },
      {
        "t": 750,
        "d": 4,
        "l": 0,
        "p": []
      },
      {
        "t": 937.5,
        "d": 5,
        "l": 0,
        "p": []
      },
      {
        "t": 1125,
        "d": 6,
        "l": 0,
        "p": []
      },
      {
        "t": 1218.75,
        "d": 7,
        "l": 0,
        "p": []
      },
      {
        "t": 1312.5,
        "d": 5,
        "l": 0,
        "p": []
      },
      {
        "t": 1500,
        "d": 5,
        "l": 0,
        "p": []
      },
      {
        "t": 1593.75,
        "d": 7,
        "l": 0,
        "p": []
      },
      {
        "t": 1687.5,
        "d": 6,
        "l": 0,
        "p": []
      },
      {
        "t": 1781.25,
        "d": 4,
        "l": 0,
        "p": []
      },
      {
        "t": 2062.5,
        "d": 7,
        "l": 0,
        "p": []
      },
      {
        "t": 2250,
        "d": 5,
        "l": 0,
        "p": []
      },
      {
        "t": 2437.5,
        "d": 4,
        "l": 0,
        "p": []
      },
      {
        "t": 3000,
        "d": 3,
        "l": 0,
        "p": []
      },
      {
        "t": 3187.5,
        "d": 2,
        "l": 0,
        "p": []
      },
      {
        "t": 3375,
        "d": 0,
        "l": 0,
        "p": []
      },
      {
        "t": 3562.5,
        "d": 2,
        "l": 0,
        "p": []
      },
      {
        "t": 3750,
        "d": 3,
        "l": 0,
        "p": []
      },
      {
        "t": 3937.5,
        "d": 2,
        "l": 0,
        "p": []
      },
      {
        "t": 4125,
        "d": 0,
        "l": 0,
        "p": []
      },
      {
        "t": 4312.5,
        "d": 1,
        "l": 0,
        "p": []
      },
      {
        "t": 4500,
        "d": 3,
        "l": 0,
        "p": []
      },
      {
        "t": 4687.5,
        "d": 0,
        "l": 0,
        "p": []
      },
      {
        "t": 4875,
        "d": 3,
        "l": 0,
        "p": []
      },
      {
        "t": 5156.25,
        "d": 2,
        "l": 0,
        "p": []
      },
      {
        "t": 5437.5,
        "d": 0,
        "l": 0,
        "p": []
      },
      {
        "t": 5625,
        "d": 2,
        "l": 0,
        "p": []
      },
      {
        "t": 6000,
        "d": 6,
        "l": 0,
        "p": []
      },
      {
        "t": 6187.5,
        "d": 4,
        "l": 0,
        "p": []
      },
      {
        "t": 6375,
        "d": 6,
        "l": 0,
        "p": []
      },
      {
        "t": 6562.5,
        "d": 4,
        "l": 0,
        "p": []
      },
      {
        "t": 6656.25,
        "d": 7,
        "l": 0,
        "p": []
      },
      {
        "t": 6750,
        "d": 6,
        "l": 0,
        "p": []
      },
      {
        "t": 6843.75,
        "d": 5,
        "l": 0,
        "p": []
      },
      {
        "t": 6937.5,
        "d": 6,
        "l": 0,
        "p": []
      },
      {
        "t": 7125,
        "d": 4,
        "l": 0,
        "p": []
      },
      {
        "t": 7500,
        "d": 4,
        "l": 0,
        "p": []
      },
      {
        "t": 7593.75,
        "d": 5,
        "l": 0,
        "p": []
      },
      {
        "t": 7687.5,
        "d": 7,
        "l": 0,
        "p": []
      },
      {
        "t": 7875,
        "d": 6,
        "l": 0,
        "p": []
      },
      {
        "t": 8062.5,
        "d": 6,
        "l": 0,
        "p": []
      },
      {
        "t": 8156.25,
        "d": 5,
        "l": 0,
        "p": []
      },
      {
        "t": 8250,
        "d": 6,
        "l": 0,
        "p": []
      },
      {
        "t": 8437.5,
        "d": 4,
        "l": 0,
        "p": []
      },
      {
        "t": 8625,
        "d": 7,
        "l": 0,
        "p": []
      },
      {
        "t": 9000,
        "d": 1,
        "l": 0,
        "p": []
      },
      {
        "t": 9187.5,
        "d": 2,
        "l": 0,
        "p": []
      },
      {
        "t": 9375,
        "d": 1,
        "l": 0,
        "p": []
      },
      {
        "t": 9562.5,
        "d": 2,
        "l": 0,
        "p": []
      },
      {
        "t": 9656.25,
        "d": 3,
        "l": 0,
        "p": []
      },
      {
        "t": 9750,
        "d": 0,
        "l": 0,
        "p": []
      },
      {
        "t": 9843.75,
        "d": 2,
        "l": 0,
        "p": []
      },
      {
        "t": 9937.5,
        "d": 1,
        "l": 0,
        "p": []
      },
      {
        "t": 10125,
        "d": 2,
        "l": 0,
        "p": []
      },
      {
        "t": 10500,
        "d": 2,
        "l": 0,
        "p": []
      },
      {
        "t": 10593.75,
        "d": 1,
        "l": 0,
        "p": []
      },
      {
        "t": 10687.5,
        "d": 3,
        "l": 0,
        "p": []
      },
      {
        "t": 10875,
        "d": 2,
        "l": 0,
        "p": []
      },
      {
        "t": 11062.5,
        "d": 0,
        "l": 0,
        "p": []
      },
      {
        "t": 11156.25,
        "d": 2,
        "l": 0,
        "p": []
      },
      {
        "t": 11250,
        "d": 1,
        "l": 0,
        "p": []
      },
      {
        "t": 11437.5,
        "d": 3,
        "l": 0,
        "p": []
      },
      {
        "t": 11625,
        "d": 2,
        "l": 0,
        "p": []
      },
      {
        "t": 12000,
        "d": 4,
        "l": 0,
        "p": []
      },
      {
        "t": 12187.5,
        "d": 7,
        "l": 0,
        "p": []
      },
      {
        "t": 12375,
        "d": 6,
        "l": 0,
        "p": []
      },
      {
        "t": 12562.5,
        "d": 5,
        "l": 0,
        "p": []
      },
      {
        "t": 12750,
        "d": 3,
        "l": 0,
        "p": []
      },
      {
        "t": 12937.5,
        "d": 0,
        "l": 0,
        "p": []
      },
      {
        "t": 13125,
        "d": 2,
        "l": 0,
        "p": []
      },
      {
        "t": 13312.5,
        "d": 1,
        "l": 0,
        "p": []
      },
      {
        "t": 13500,
        "d": 4,
        "l": 0,
        "p": []
      },
      {
        "t": 13687.5,
        "d": 5,
        "l": 0,
        "p": []
      },
      {
        "t": 13875,
        "d": 4,
        "l": 0,
        "p": []
      },
      {
        "t": 14062.5,
        "d": 5,
        "l": 0,
        "p": []
      },
      {
        "t": 14250,
        "d": 3,
        "l": 0,
        "p": []
      },
      {
        "t": 14437.5,
        "d": 1,
        "l": 0,
        "p": []
      },
      {
        "t": 14625,
        "d": 3,
        "l": 0,
        "p": []
      },
      {
        "t": 14812.5,
        "d": 1,
        "l": 0,
        "p": []
      },
      {
        "t": 15000,
        "d": 6,
        "l": 0,
        "p": []
      },
      {
        "t": 15000,
        "d": 2,
        "l": 0,
        "p": []
      },
      {
        "t": 15187.5,
        "d": 5,
        "l": 0,
        "p": []
      },
      {
        "t": 15187.5,
        "d": 1,
        "l": 0,
        "p": []
      },
      {
        "t": 15375,
        "d": 6,
        "l": 0,
        "p": []
      },
      {
        "t": 15375,
        "d": 2,
        "l": 0,
        "p": []
      },
      {
        "t": 15562.5,
        "d": 5,
        "l": 0,
        "p": []
      },
      {
        "t": 15562.5,
        "d": 1,
        "l": 0,
        "p": []
      },
      {
        "t": 15750,
        "d": 4,
        "l": 0,
        "p": []
      },
      {
        "t": 15750,
        "d": 3,
        "l": 0,
        "p": []
      },
      {
        "t": 15843.75,
        "d": 7,
        "l": 0,
        "p": []
      },
      {
        "t": 15843.75,
        "d": 0,
        "l": 0,
        "p": []
      },
      {
        "t": 15937.5,
        "d": 6,
        "l": 0,
        "p": []
      },
      {
        "t": 15937.5,
        "d": 2,
        "l": 0,
        "p": []
      },
      {
        "t": 16125,
        "d": 5,
        "l": 0,
        "p": []
      },
      {
        "t": 16125,
        "d": 1,
        "l": 0,
        "p": []
      },
      {
        "t": 16218.75,
        "d": 6,
        "l": 0,
        "p": []
      },
      {
        "t": 16218.75,
        "d": 2,
        "l": 0,
        "p": []
      },
      {
        "t": 16312.5,
        "d": 1,
        "l": 0,
        "p": []
      },
      {
        "t": 16500,
        "d": 4,
        "l": 0,
        "p": []
      },
      {
        "t": 16593.75,
        "d": 7,
        "l": 0,
        "p": []
      },
      {
        "t": 16687.5,
        "d": 5,
        "l": 281.25,
        "p": []
      },
      {
        "t": 17062.5,
        "d": 7,
        "l": 0,
        "p": []
      },
      {
        "t": 17250,
        "d": 6,
        "l": 0,
        "p": []
      },
      {
        "t": 17343.75,
        "d": 4,
        "l": 0,
        "p": []
      },
      {
        "t": 17437.5,
        "d": 7,
        "l": 0,
        "p": []
      },
      {
        "t": 17531.25,
        "d": 6,
        "l": 0,
        "p": []
      },
      {
        "t": 17625,
        "d": 4,
        "l": 0,
        "p": []
      },
      {
        "t": 17718.75,
        "d": 5,
        "l": 187.5,
        "p": []
      },
      {
        "t": 18000,
        "d": 3,
        "l": 0,
        "p": []
      },
      {
        "t": 18093.75,
        "d": 0,
        "l": 0,
        "p": []
      },
      {
        "t": 18187.5,
        "d": 3,
        "l": 0,
        "p": []
      },
      {
        "t": 18562.5,
        "d": 1,
        "l": 0,
        "p": []
      },
      {
        "t": 18750,
        "d": 1,
        "l": 0,
        "p": []
      },
      {
        "t": 18843.75,
        "d": 0,
        "l": 0,
        "p": []
      },
      {
        "t": 18937.5,
        "d": 3,
        "l": 0,
        "p": []
      },
      {
        "t": 19031.25,
        "d": 2,
        "l": 0,
        "p": []
      },
      {
        "t": 19218.75,
        "d": 3,
        "l": 0,
        "p": []
      },
      {
        "t": 19312.5,
        "d": 1,
        "l": 0,
        "p": []
      },
      {
        "t": 19500,
        "d": 2,
        "l": 0,
        "p": []
      },
      {
        "t": 19687.5,
        "d": 0,
        "l": 0,
        "p": []
      },
      {
        "t": 19875,
        "d": 2,
        "l": 0,
        "p": []
      },
      {
        "t": 20062.5,
        "d": 3,
        "l": 0,
        "p": []
      },
      {
        "t": 20250,
        "d": 1,
        "l": 0,
        "p": []
      },
      {
        "t": 20437.5,
        "d": 2,
        "l": 0,
        "p": []
      },
      {
        "t": 20625,
        "d": 3,
        "l": 0,
        "p": []
      },
      {
        "t": 20812.5,
        "d": 1,
        "l": 0,
        "p": []
      },
      {
        "t": 21000,
        "d": 0,
        "l": 0,
        "p": []
      },
      {
        "t": 21187.5,
        "d": 3,
        "l": 0,
        "p": []
      },
      {
        "t": 21375,
        "d": 2,
        "l": 0,
        "p": []
      },
      {
        "t": 21562.5,
        "d": 1,
        "l": 0,
        "p": []
      },
      {
        "t": 21750,
        "d": 0,
        "l": 281.25,
        "p": []
      },
      {
        "t": 22125,
        "d": 2,
        "l": 281.25,
        "p": []
      },
      {
        "t": 22500,
        "d": 1,
        "l": 281.25,
        "p": []
      },
      {
        "t": 22875,
        "d": 2,
        "l": 281.25,
        "p": []
      },
      {
        "t": 23250,
        "d": 1,
        "l": 281.25,
        "p": []
      },
      {
        "t": 23250,
        "d": 3,
        "l": 281.25,
        "p": []
      },
      {
        "t": 23625,
        "d": 2,
        "l": 281.25,
        "p": []
      },
      {
        "t": 23625,
        "d": 0,
        "l": 281.25,
        "p": []
      },
      {
        "t": 24000,
        "d": 4,
        "l": 0,
        "p": []
      },
      {
        "t": 24000,
        "d": 6,
        "l": 0,
        "p": []
      },
      {
        "t": 24375,
        "d": 5,
        "l": 0,
        "p": []
      },
      {
        "t": 24375,
        "d": 7,
        "l": 0,
        "p": []
      },
      {
        "t": 24750,
        "d": 7,
        "l": 0,
        "p": []
      },
      {
        "t": 24750,
        "d": 4,
        "l": 0,
        "p": []
      },
      {
        "t": 25125,
        "d": 5,
        "l": 0,
        "p": []
      },
      {
        "t": 25125,
        "d": 6,
        "l": 0,
        "p": []
      },
      {
        "t": 25500,
        "d": 4,
        "l": 0,
        "p": []
      },
      {
        "t": 25500,
        "d": 5,
        "l": 0,
        "p": []
      },
      {
        "t": 26250,
        "d": 6,
        "l": 0,
        "p": []
      },
      {
        "t": 26437.5,
        "d": 7,
        "l": 0,
        "p": []
      },
      {
        "t": 26625,
        "d": 5,
        "l": 0,
        "p": []
      },
      {
        "t": 26812.5,
        "d": 4,
        "l": 0,
        "p": []
      },
      {
        "t": 27000,
        "d": 5,
        "l": 0,
        "p": []
      },
      {
        "t": 27187.5,
        "d": 6,
        "l": 0,
        "p": []
      },
      {
        "t": 27375,
        "d": 5,
        "l": 0,
        "p": []
      },
      {
        "t": 27562.5,
        "d": 4,
        "l": 0,
        "p": []
      },
      {
        "t": 27750,
        "d": 6,
        "l": 0,
        "p": []
      },
      {
        "t": 27937.5,
        "d": 5,
        "l": 0,
        "p": []
      },
      {
        "t": 28125,
        "d": 4,
        "l": 0,
        "p": []
      },
      {
        "t": 28500,
        "d": 2,
        "l": 0,
        "p": []
      },
      {
        "t": 28875,
        "d": 3,
        "l": 0,
        "p": []
      },
      {
        "t": 29062.5,
        "d": 1,
        "l": 0,
        "p": []
      },
      {
        "t": 29250,
        "d": 0,
        "l": 0,
        "p": []
      },
      {
        "t": 29437.5,
        "d": 2,
        "l": 0,
        "p": []
      },
      {
        "t": 29625,
        "d": 1,
        "l": 0,
        "p": []
      },
      {
        "t": 29812.5,
        "d": 3,
        "l": 0,
        "p": []
      },
      {
        "t": 30000,
        "d": 0,
        "l": 0,
        "p": []
      },
      {
        "t": 30375,
        "d": 2,
        "l": 0,
        "p": []
      },
      {
        "t": 30562.5,
        "d": 1,
        "l": 0,
        "p": []
      },
      {
        "t": 30750,
        "d": 2,
        "l": 0,
        "p": []
      },
      {
        "t": 30937.5,
        "d": 3,
        "l": 0,
        "p": []
      },
      {
        "t": 38625,
        "d": 5,
        "l": 468.75,
        "p": []
      }
    ]
  },
  "generatedBy": "Friday Night Funkin' - v0.7.5"
}
